twitter_list_mgmt/__init__.py
twitter_list_mgmt/auth.py
twitter_list_mgmt/helpers.py
twitter_list_mgmt/twitter_list_mgmt.py
twitter_list_mgmt-0.1.2.dist-info/METADATA
twitter_list_mgmt-0.1.2.dist-info/WHEEL
twitter_list_mgmt-0.1.2.dist-info/top_level.txt
twitter_list_mgmt-0.1.2.dist-info/RECORD
