Metadata-Version: 2.1
Name: twitter-list-mgmt
Version: 0.1.2
Summary: A Python package for managing Twitter lists
Home-page: https://github.com/shijithpk/twitter-list-management
Author: Shijith Kunhitty
Author-email: mail@shijith.com
License: Unlicense
Project-URL: Source, https://github.com/shijithpk/twitter-list-management
Keywords: twitter,lists,lifehack,lifehacker
Platform: UNKNOWN
Classifier: Development Status :: 3 - Alpha
Classifier: Environment :: Console
Classifier: License :: OSI Approved :: The Unlicense (Unlicense)
Classifier: Programming Language :: Python :: 3.6
Classifier: Programming Language :: Python :: 3.7
Classifier: Programming Language :: Python :: 3.8
Classifier: Programming Language :: Python :: 3.9
Requires-Python: >=3.6
Requires-Dist: tweepy (>=4.0.0a0)
Requires-Dist: pandas (>=1.2.3)
